server/__init__.py
server/server.py
server/server_database.py
server/server_gui.py
server/common/__init__.py
server/common/decos.py
server/common/descryptors.py
server/common/errors.py
server/common/metaclasses.py
server/common/utils.py
server/common/variables.py
server/doc/__init__.py
server/doc/source/__init__.py
server/doc/source/conf.py
server/logs/__init__.py
server/logs/configs/__init__.py
server/logs/configs/config_client_log.py
server/logs/configs/config_server_log.py
server/server/__init__.py
server/server/add_user.py
server/server/config_window.py
server/server/core.py
server/server/database.py
server/server/main_window.py
server/server/remove_user.py
server/server/stat_window.py
server/unit_tests/__init__.py
server/unit_tests/test_client.py
server/unit_tests/test_server.py
server/unit_tests/test_utils.py
the_me_mess_server-0.0.1.dist-info/METADATA
the_me_mess_server-0.0.1.dist-info/WHEEL
the_me_mess_server-0.0.1.dist-info/top_level.txt
the_me_mess_server-0.0.1.dist-info/RECORD
