Metadata-Version: 2.1
Name: the-me-mess-server
Version: 0.0.1
Summary: the_me_mess_server
Home-page: UNKNOWN
Author: the_me
Author-email: the_me@live.ru
License: UNKNOWN
Platform: UNKNOWN
Requires-Dist: PyQt5
Requires-Dist: sqlalchemy
Requires-Dist: pycryptodome
Requires-Dist: pycryptodomex
